ctx/__init__.py
ctx/cli.py
ctx_codebase_helper-0.4.0.dist-info/METADATA
ctx_codebase_helper-0.4.0.dist-info/WHEEL
ctx_codebase_helper-0.4.0.dist-info/entry_points.txt
ctx_codebase_helper-0.4.0.dist-info/top_level.txt
ctx_codebase_helper-0.4.0.dist-info/RECORD
