Metadata-Version: 2.1
Name: ctx-codebase-helper
Version: 0.4.0
Summary: CLI tool to generate codebase context for LLMs
Home-page: https://github.com/Aditya-en/ctx-cli
Author: Aditya Sahani
Classifier: License :: OSI Approved :: MIT License
Classifier: Programming Language :: Python :: 3
Classifier: Operating System :: OS Independent
Requires-Python: >=3.6
Requires-Dist: gitignore-parser
Requires-Dist: pathspec
Requires-Dist: pyperclip
